apart/__init__.py
apart-0.0.0.dist-info/METADATA
apart-0.0.0.dist-info/WHEEL
apart-0.0.0.dist-info/top_level.txt
apart-0.0.0.dist-info/RECORD
