Metadata-Version: 2.1
Name: apart
Version: 0.0.0
Summary: Partial trace and partial transpose for matrices with Kronecker product structure.
Home-page: https://provaznik.pro/apart
Author: Jan Provaznik
Author-email: jan@provaznik.pro
License: LGPL
